{
  "input_nodes": [
    {
      "bias": -211.6471,
      "value": 1.0
    },
    {
      "bias": -295.15396,
      "value": 1.0
    }
  ],
  "hidden_nodes": [
    [
      {
        "bias": 0.50712967,
        "value": 1.0,
        "weights": [
          4.133083,
          17.340746
        ]
      },
      {
        "bias": -71.22418,
        "value": 1.0,
        "weights": [
          0.6756928,
          10.357359
        ]
      },
      {
        "bias": -6.7009425,
        "value": 1.0,
        "weights": [
          -3.9063075,
          -3.2382336
        ]
      },
      {
        "bias": -10.189129,
        "value": 1.0,
        "weights": [
          16.507425,
          -6.944144
        ]
      }
    ],
    [
      {
        "bias": -50.42328,
        "value": 1.0,
        "weights": [
          4.4908643,
          -0.5527975,
          -2.1059306,
          1.4241816
        ]
      },
      {
        "bias": -94.62217,
        "value": 1.0,
        "weights": [
          4.268191,
          -4.765692,
          8.382764,
          1.3966038
        ]
      },
      {
        "bias": -81.93424,
        "value": 1.0,
        "weights": [
          7.0648274,
          1.5997581,
          1.3993186,
          1.2723264
        ]
      },
      {
        "bias": 11.088065,
        "value": 1.0,
        "weights": [
          0.21648325,
          3.384276,
          -1.4885478,
          -3.3955305
        ]
      }
    ]
  ],
  "output_nodes": [
    {
      "bias": 48.802265,
      "value": 1.0,
      "weights": [
        -4.3963213,
        -4.99438,
        5.7960615,
        -2.4393907
      ]
    },
    {
      "bias": -9.897491,
      "value": 1.0,
      "weights": [
        1.8939489,
        0.92143,
        1.8430852,
        4.1542773
      ]
    }
  ]
}